xum/__init__.py
xum/config.py
xum/fetchers.py
xum/fzf.py
xum/main.py
xum/tmux.py
xum/utils.py
xum-0.3.4.dist-info/licenses/LICENSE
xum-0.3.4.dist-info/METADATA
xum-0.3.4.dist-info/WHEEL
xum-0.3.4.dist-info/entry_points.txt
xum-0.3.4.dist-info/top_level.txt
xum-0.3.4.dist-info/RECORD
