Metadata-Version: 2.4
Name: xum
Version: 0.3.4
Summary: Manage Tmux session for selected folders and SSH hosts
Author: pbignardi
Project-URL: Repository, https://github.com/pbignardi/xum.git
Requires-Python: >=3.11
License-File: LICENSE
Dynamic: license-file
